{
  "layout": "5",
  "type": "MUSIC",
  "key": "53510886",
  "title": "Bloody Mary",
  "subtitle": "Lady Gaga",
  "images": {
    "background": "https://is2-ssl.mzstatic.com/image/thumb/Music122/v4/2c/7d/5e/2c7d5ec0-bad6-5fb6-08f2-ccfd94aa2985/pr_source.png/800x800cc.jpg",
    "coverart": "https://is4-ssl.mzstatic.com/image/thumb/Music124/v4/65/1b/f6/651bf621-fcf2-e3ba-4ef4-22645f26e0a0/11UMGIM12477.rgb.jpg/400x400cc.jpg",
    "coverarthq": "https://is4-ssl.mzstatic.com/image/thumb/Music124/v4/65/1b/f6/651bf621-fcf2-e3ba-4ef4-22645f26e0a0/11UMGIM12477.rgb.jpg/400x400cc.jpg",
    "joecolor": "b:040809p:f3f2eds:c9c9c9t:c3c3c0q:a1a2a2"
  },
  "share": {
    "subject": "Bloody Mary - Lady Gaga",
    "text": "I used Shazam to discover Bloody Mary by Lady Gaga.",
    "href": "https://www.shazam.com/track/53510886/bloody-mary",
    "image": "https://is4-ssl.mzstatic.com/image/thumb/Music124/v4/65/1b/f6/651bf621-fcf2-e3ba-4ef4-22645f26e0a0/11UMGIM12477.rgb.jpg/400x400cc.jpg",
    "twitter": "I used @Shazam to discover Bloody Mary by Lady Gaga.",
    "html": "https://www.shazam.com/snippets/email-share/53510886?lang=en&country=GB",
    "avatar": "https://is2-ssl.mzstatic.com/image/thumb/Music122/v4/2c/7d/5e/2c7d5ec0-bad6-5fb6-08f2-ccfd94aa2985/pr_source.png/800x800cc.jpg",
    "snapchat": "https://www.shazam.com/partner/sc/track/53510886"
  },
  "hub": {
    "type": "APPLEMUSIC",
    "image": "https://images.shazam.com/static/icons/hub/web/v5/applemusic.png",
    "actions": [
      {
        "name": "apple",
        "type": "applemusicplay",
        "id": "1440824272"
      },
      {
        "name": "apple",
        "type": "uri",
        "uri": "https://audio-ssl.itunes.apple.com/itunes-assets/AudioPreview122/v4/c7/b0/df/c7b0dfe8-e1dc-1bda-88b0-0dc9b67e1b1b/mzaf_15572490037611837314.plus.aac.ep.m4a"
      }
    ],
    "options": [
      {
        "caption": "OPEN",
        "actions": [
          {
            "name": "hub:applemusic:deeplink",
            "type": "applemusicopen",
            "uri": "https://music.apple.com/gb/album/bloody-mary/1440824019?i=1440824272&mttnagencyid=s2n&mttnsiteid=125115&mttn3pid=Apple-Shazam&mttnsub1=Shazam_web&mttnsub2=5348615A-616D-3235-3830-44754D6D5973&itscg=30201&app=music&itsct=Shazam_web"
          },
          {
            "name": "hub:applemusic:deeplink",
            "type": "uri",
            "uri": "https://music.apple.com/gb/album/bloody-mary/1440824019?i=1440824272&mttnagencyid=s2n&mttnsiteid=125115&mttn3pid=Apple-Shazam&mttnsub1=Shazam_web&mttnsub2=5348615A-616D-3235-3830-44754D6D5973&itscg=30201&app=music&itsct=Shazam_web"
          }
        ],
        "beacondata": {
          "type": "open",
          "providername": "applemusic"
        },
        "image": "https://images.shazam.com/static/icons/hub/web/v5/overflow-open-option.png",
        "type": "open",
        "listcaption": "Open in Apple Music",
        "overflowimage": "https://images.shazam.com/static/icons/hub/web/v5/applemusic-overflow.png",
        "colouroverflowimage": false,
        "providername": "applemusic"
      }
    ],
    "explicit": false,
    "displayname": "APPLE MUSIC"
  },
  "sections": [
    {
      "type": "SONG",
      "metapages": [
        {
          "image": "https://is2-ssl.mzstatic.com/image/thumb/Music122/v4/2c/7d/5e/2c7d5ec0-bad6-5fb6-08f2-ccfd94aa2985/pr_source.png/800x800cc.jpg",
          "caption": "Lady Gaga"
        },
        {
          "image": "https://is4-ssl.mzstatic.com/image/thumb/Music124/v4/65/1b/f6/651bf621-fcf2-e3ba-4ef4-22645f26e0a0/11UMGIM12477.rgb.jpg/400x400cc.jpg",
          "caption": "Bloody Mary"
        }
      ],
      "tabname": "Song",
      "metadata": [
        {
          "title": "Album",
          "text": "Born This Way"
        },
        {
          "title": "Label",
          "text": "Interscope"
        },
        {
          "title": "Released",
          "text": "2011"
        }
      ]
    },
    {
      "type": "LYRICS",
      "text": [
        "Money",
        "",
        "Oh",
        "",
        "Love is just a history that they may prove",
        "And when you're gone",
        "I'll tell them my religion's you",
        "When Punktious comes to kill the king upon his throne",
        "I'm ready for their stones",
        "",
        "I'll dance, dance, dance",
        "With my hands, hands, hands",
        "Above my head, head, head",
        "Like Jesus said",
        "I'm gonna dance, dance, dance",
        "With my hands, hands, hands above my head",
        "Hands together, forgive him before he's dead, because",
        "",
        "I won't cry for you",
        "I won't crucify the things you do",
        "I won't cry for you",
        "See (see), when you're gone, I'll still be Bloody Mary",
        "",
        "Love",
        "",
        "We are not just art for Michelangelo to carve",
        "He can't rewrite the aggro of my furied heart",
        "I'll wait on mountain tops in Paris, cold",
        "J'veux pas mourir toute seule",
        "",
        "I'll dance, dance, dance",
        "With my hands, hands, hands",
        "Above my head, head, head",
        "Like Jesus said",
        "I'm gonna dance, dance, dance",
        "With my hands, hands, hands above my head",
        "Hands together, forgive him before he's dead, because",
        "",
        "I won't cry for you",
        "I won't crucify the things you do",
        "I won't cry for you",
        "See (see), when you're gone, I'll still be Bloody Mary",
        "",
        "Love",
        "",
        "Gaga, Gaga",
        "Gaga, Gaga",
        "Gaga, Gaga",
        "Gaga, Gaga",
        "",
        "Dum dum, da-di-da",
        "Dum dum, da-di-da-dadda-da-di-da",
        "Dum dum, da-di-da",
        "Dum dum, da-di-da",
        "Dum dum, da-di-da-dadda-da-di-da",
        "Dum dum, da-di-da",
        "",
        "I won't cry for you",
        "I won't crucify the things you do, do, do",
        "I won't cry for you",
        "See (see), when you're gone, I'll still be Bloody Mary",
        "",
        "Oh-oh-oh-oh-oh",
        "Oh-oh-oh-oh-oh",
        "Oh-oh-oh-oh-oh",
        "Oh-oh-oh-oh-oh",
        "Oh-oh-oh-oh-oh",
        "Oh-oh-oh-oh-oh",
        "Oh-oh-oh-oh-oh",
        "Oh-oh-oh-oh-oh",
        "",
        "Líberate, mi amor"
      ],
      "footer": "Writer(s): Fernando Garibay, William Grigahcine, Paul Blair, Clinton C Sparks, Stefani Germanotta\nLyrics powered by www.musixmatch.com",
      "tabname": "Lyrics",
      "beacondata": {
        "lyricsid": "29696569",
        "providername": "musixmatch",
        "commontrackid": "9701438"
      }
    },
    {
      "type": "VIDEO",
      "tabname": "Video"
    },
    {
      "type": "RELATED",
      "tabname": "Related"
    }
  ],
  "url": "https://www.shazam.com/track/53510886/bloody-mary",
  "artists": [
    {
      "alias": "lady-gaga",
      "id": "42",
      "adamid": "277293880"
    }
  ],
  "alias": "bloody-mary",
  "isrc": "USUM71106449",
  "genres": {
    "primary": "Pop"
  },
  "urlparams": {
    "{tracktitle}": "Bloody+Mary",
    "{trackartist}": "Lady+Gaga"
  },
  "highlightsurls": {},
  "albumadamid": "1440824019",
  "trackadamid": "1440824272",
  "releasedate": "23-05-2011"
}
